theTwelvePassGen/__init__.py
theTwelvePassGen/the12PassGen.py
theTwelvePassGen-0.0.1.dist-info/LICENSE
theTwelvePassGen-0.0.1.dist-info/METADATA
theTwelvePassGen-0.0.1.dist-info/WHEEL
theTwelvePassGen-0.0.1.dist-info/top_level.txt
theTwelvePassGen-0.0.1.dist-info/RECORD
