Metadata-Version: 2.1
Name: theTwelvePassGen
Version: 0.0.1
Summary: A password generator
Home-page: https://github.com/pypa/sampleproject
Author: BaddSky
Author-email: vgiam35@mgail.com
Project-URL: Bug Tracker, https://github.com/pypa/sampleproject/issues
Classifier: Programming Language :: Python :: 3
Classifier: License :: OSI Approved :: MIT License
Classifier: Operating System :: OS Independent
Requires-Python: >=3.6
License-File: LICENSE
